py_homepass/__init__.py
py_homepass/const.py
py_homepass/py_homepass.py
py_homepass-0.0.1.dist-info/WHEEL
py_homepass-0.0.1.dist-info/METADATA
py_homepass-0.0.1.dist-info/RECORD
